{
    "version": 8,
    "name": "MapLibre Style",
    "sources": {
        "osm": {
            "type": "raster",
            "tiles": [
                "https://a.tile.openstreetmap.org/{z}/{x}/{y}.png",
                "https://b.tile.openstreetmap.org/{z}/{x}/{y}.png",
                "https://c.tile.openstreetmap.org/{z}/{x}/{y}.png"
            ],
            "tileSize": 256,
            "attribution": "© OpenStreetMap contributors"
        }
    },
    "layers": [
        {
            "id": "background",
            "type": "raster",
            "source": "osm",
            "minzoom": 0,
            "maxzoom": 22
        }
    ],
    "sprite": "",
    "glyphs": "https://demotiles.maplibre.org/font/{fontstack}/{range}.pbf",
    "color-adjustment": {
        "grayscale": 1
    }
}